{
  "_children": [
    {
      "_data": {
        "Study Area": "SA-1",
        "Population Unit": "PU-1",
        "Block ID/SU ID": "BISID-1",
        "UTM Zone": "8",
        "Easting": "1",
        "Northing": "1",
        "Datum": "NAD27",
        "Lat (DD)": "lat",
        "Long (DD)": "long",
        "Species": "S-ELK",
        "Group Label": "GL-1",
        "Date": "27/Feb/23",
        "Unclassified Bulls": "16",
        "Cows": "17",
        "Calves": "18",
        "Adult Unclassified Sex": "19",
        "Yearling - Unclassified Sex": "20",
        "Unclassified Age/Sex": "21",
        "Total Count": "111",
        "Sign Type": "Body Parts",
        "Sign Count": "1",
        "Age of Sign": "Hour",
        "Topography": "flat",
        "Habitat": "Avalanche Path",
        "Veg Cover (%)": "1",
        "Snow Cover (%)": "1",
        "Activity": "Moving",
        "Number of Marked Animals Observed": "100",
        "Survey or Telemetry Search": "Survey",
        "Photos": "some_phtos",
        "Observation Comments": "coments son"
      },
      "_name": "Observations",
      "_key": "SA-1:BISID-1",
      "_parentKey": "",
      "_type": "root",
      "_row": 0,
      "_childKeys": [
        "GL-1"
      ],
      "_children": [
        {
          "_data": {
            "Group Label": "GL-1",
            "Date": "2023-1010",
            "Targeted or Non-Targeted": "Targeted",
            "Wildlife Health ID": "wlid",
            "Animal ID": "aid",
            "Telemetry Device ID": "tdid",
            "Collar/Tag Frequency": "ctid",
            "Frequency Unit": "MHz",
            "Right Ear Tag ID": "retid",
            "Right Ear Tag Colour": "retc",
            "Left Ear Tag ID": "letid",
            "Left Ear Tag Colour": "letc",
            "Marked Animals Comments": "marked comments"
          },
          "_name": "Marked Animals",
          "_key": "wlid:aid:tdid",
          "_parentKey": "GL-1",
          "_type": "",
          "_row": 0,
          "_childKeys": [],
          "_children": []
        }
      ]
    }
  ]
}